src/cli_report/__init__.py
src/cli_report/__main__.py
src/cli_report/report.py
report_racing_vasiliy-0.0.2.dist-info/METADATA
report_racing_vasiliy-0.0.2.dist-info/WHEEL
report_racing_vasiliy-0.0.2.dist-info/RECORD
