Metadata-Version: 2.1
Name: report-racing-vasiliy
Version: 0.0.2
Summary: A small example package
Project-URL: Homepage, https://git.foxminded.ua/foxstudent102159/task-6-report-of-monaco-2018-racing
Project-URL: Bug Tracker, https://git.foxminded.ua/foxstudent102159/task-6-report-of-monaco-2018-racing/-/issues
Author-email: Vasiliy Bagriy <devilinde25@gmail.com>
Classifier: License :: OSI Approved :: MIT License
Classifier: Operating System :: OS Independent
Classifier: Programming Language :: Python :: 3
Requires-Python: >=3.10
